LICENSE.txt
MANIFEST.in
Makefile
README.rst
VERSION
setup.cfg
setup.py
docs/Makefile
docs/source/conf.py
docs/source/index.rst
docs/source/syntax.rst
docs/source/why.rst
plasmic/__init__.py
plasmic/parse.py
plasmic.egg-info/PKG-INFO
plasmic.egg-info/SOURCES.txt
plasmic.egg-info/dependency_links.txt
plasmic.egg-info/top_level.txt