Metadata-Version: 1.1
Name: plasmic
Version: 0.2.1
Summary: Parse configuration files written in a Python-like syntax
Home-page: http://plasmic.readthedocs.org/
Author: Karl O. Pinc
Author-email: plasmic@googlegroups.com
License: LGPLv3+
Keywords: cfg conf config configparser configuration file interpolation parser parsing pcf python replacement
Platform: UNKNOWN
Classifier: Development Status :: 1 - Planning
Classifier: Intended Audience :: Developers
Classifier: Topic :: Software Development :: Libraries
Classifier: Topic :: Software Development :: Libraries :: Python Modules
Classifier: License :: OSI Approved :: GNU General Public License v3 or later (GPLv3+)
Classifier: Programming Language :: Python :: 2
Classifier: Programming Language :: Python :: 2.6
Classifier: Programming Language :: Python :: 2.7
Classifier: Programming Language :: Python :: 3
Classifier: Programming Language :: Python :: 3.3
Classifier: Programming Language :: Python :: 3.4
Classifier: Programming Language :: Python :: 3.5
